o2sclpy/__init__.py
o2sclpy/base.py
o2sclpy/bl_gltf_import.py
o2sclpy/bl_gltf_six.py
o2sclpy/bl_gltf_yaw.py
o2sclpy/cap_cout.py
o2sclpy/classify.py
o2sclpy/dimred.py
o2sclpy/doc_data.py
o2sclpy/eos.py
o2sclpy/gmm.py
o2sclpy/hdf.py
o2sclpy/interpm.py
o2sclpy/kde.py
o2sclpy/link_o2scl.py
o2sclpy/nflows.py
o2sclpy/nuclei.py
o2sclpy/o2graph.py
o2sclpy/o2graph_plotter.py
o2sclpy/other.py
o2sclpy/part.py
o2sclpy/plot_base.py
o2sclpy/plot_info.py
o2sclpy/string.py
o2sclpy/td_plot_base.py
o2sclpy/utils.py
o2sclpy/yt_plot_base.py
o2sclpy/test/test_classify.py
o2sclpy/test/test_cpp_class.py
o2sclpy/test/test_den_plot.py
o2sclpy/test/test_dimred.py
o2sclpy/test/test_gmm.py
o2sclpy/test/test_interpm.py
o2sclpy/test/test_kde.py
o2sclpy/test/test_lib_settings.py
o2sclpy/test/test_nflows.py
o2sclpy/test/test_table.py
o2sclpy/test/test_table3d.py
o2sclpy/test/test_table_units.py
o2sclpy/test/test_tensor.py
o2sclpy/test/test_tensor_grid.py
o2sclpy/test/test_ug.py
o2sclpy/test/test_vec_stats.py
o2sclpy-0.931.1.dist-info/licenses/LICENSE
o2sclpy-0.931.1.dist-info/METADATA
o2sclpy-0.931.1.dist-info/WHEEL
o2sclpy-0.931.1.dist-info/entry_points.txt
o2sclpy-0.931.1.dist-info/top_level.txt
o2sclpy-0.931.1.dist-info/RECORD
