Metadata-Version: 2.4
Name: o2sclpy
Version: 0.931.1
Summary: Python extensions for O2scl
Author-email: "Andrew W. Steiner" <awsteiner0@protonmail.com>
License:                     GNU GENERAL PUBLIC LICENSE
Project-URL: Homepage, http://awsteiner.org/code/o2sclpy/
Project-URL: Issues, https://github.com/awsteiner/o2sclpy/issues
Keywords: o2scl
Classifier: Development Status :: 4 - Beta
Classifier: License :: OSI Approved :: GNU General Public License v3 (GPLv3)
Classifier: Programming Language :: Python :: 3 :: Only
Classifier: Topic :: Scientific/Engineering
Requires-Python: >=3.8
License-File: LICENSE
Requires-Dist: numpy
Requires-Dist: matplotlib>=3.1
Provides-Extra: cli
Requires-Dist: yt; extra == "cli"
Requires-Dist: scikit-learn; extra == "cli"
Requires-Dist: tensorflow; extra == "cli"
Requires-Dist: scipy; extra == "cli"
Requires-Dist: torch; extra == "cli"
Requires-Dist: normflows; extra == "cli"
Requires-Dist: ipython; extra == "cli"
Requires-Dist: distro; extra == "cli"
Requires-Dist: tqdm; extra == "cli"
Dynamic: license-file
